CHANGES.rst
MANIFEST.in
README.rst
setup.py
runwsgi/__init__.py
runwsgi/__init__.pyc
runwsgi/__main__.py
runwsgi/demo.py
runwsgi/runwsgi
runwsgi/runwsgi.bat
runwsgi/runwsgi.py
runwsgi/runwsgi.pyc
runwsgi.egg-info/PKG-INFO
runwsgi.egg-info/SOURCES.txt
runwsgi.egg-info/dependency_links.txt
runwsgi.egg-info/not-zip-safe
runwsgi.egg-info/top_level.txt