Metadata-Version: 1.1
Name: runwsgi
Version: 0.0.2
Summary: A simple runner for Python wsgi application. Like Gunicorn but can run on Windows. It's to simple, so do not use at production environment.
Home-page: https://github.com/sintrb/runwsgi
Author: sintrb
Author-email: sintrb@gmail.com
License: Apache
Keywords: runwsgi wsgirunner wsgi
Platform: UNKNOWN
Classifier: Intended Audience :: Developers
Classifier: Operating System :: OS Independent
Classifier: Programming Language :: Python :: 2.7
